qqlog/__init__.py
qqlog-0.0.5.dist-info/LICENSE
qqlog-0.0.5.dist-info/METADATA
qqlog-0.0.5.dist-info/WHEEL
qqlog-0.0.5.dist-info/top_level.txt
qqlog-0.0.5.dist-info/RECORD
