Metadata-Version: 2.1
Name: qqlog
Version: 0.0.5
Summary: quick method log/exception catching
Home-page: https://github.com/sheauren/qqlog
Author: Sheauren Wang
Author-email: sheauren@gmail.com
License: UNKNOWN
Platform: UNKNOWN
Classifier: Programming Language :: Python :: 3
Classifier: License :: OSI Approved :: MIT License
Classifier: Operating System :: OS Independent
Requires-Python: >=3.5
License-File: LICENSE
